[{
  "comments": [{
    "author": {
      "login": "davies"
    },
    "body": "Is there any reason to put `--no-progress-bar` here(instead of in the end)?\n",
    "commit": "06814035d454a9b7e444b0dc657a572a6ae2f899",
    "createdAt": "2014-12-16T06:18:40Z",
    "diffHunk": "@@ -32,10 +32,11 @@ function gatherSparkSubmitOpts() {\n   APPLICATION_OPTS=()\n   while (($#)); do\n     case \"$1\" in\n-      --master | --deploy-mode | --class | --name | --jars | --py-files | --files | \\\n-      --conf | --properties-file | --driver-memory | --driver-java-options | \\\n-      --driver-library-path | --driver-class-path | --executor-memory | --driver-cores | \\\n-      --total-executor-cores | --executor-cores | --queue | --num-executors | --archives)\n+      --master | --deploy-mode | --class | --name | --jars | --no-progress-bar | \\",
    "line": 8
  }, {
    "author": {
      "login": "maropu"
    },
    "body": "No reason. Is it better to place the end?\n",
    "commit": "06814035d454a9b7e444b0dc657a572a6ae2f899",
    "createdAt": "2014-12-17T08:39:11Z",
    "diffHunk": "@@ -32,10 +32,11 @@ function gatherSparkSubmitOpts() {\n   APPLICATION_OPTS=()\n   while (($#)); do\n     case \"$1\" in\n-      --master | --deploy-mode | --class | --name | --jars | --py-files | --files | \\\n-      --conf | --properties-file | --driver-memory | --driver-java-options | \\\n-      --driver-library-path | --driver-class-path | --executor-memory | --driver-cores | \\\n-      --total-executor-cores | --executor-cores | --queue | --num-executors | --archives)\n+      --master | --deploy-mode | --class | --name | --jars | --no-progress-bar | \\",
    "line": 8
  }, {
    "author": {
      "login": "andrewor14"
    },
    "body": "please also update `bin/windows-utils.cmd`\n",
    "commit": "06814035d454a9b7e444b0dc657a572a6ae2f899",
    "createdAt": "2015-01-07T23:20:18Z",
    "diffHunk": "@@ -32,10 +32,11 @@ function gatherSparkSubmitOpts() {\n   APPLICATION_OPTS=()\n   while (($#)); do\n     case \"$1\" in\n-      --master | --deploy-mode | --class | --name | --jars | --py-files | --files | \\\n-      --conf | --properties-file | --driver-memory | --driver-java-options | \\\n-      --driver-library-path | --driver-class-path | --executor-memory | --driver-cores | \\\n-      --total-executor-cores | --executor-cores | --queue | --num-executors | --archives)\n+      --master | --deploy-mode | --class | --name | --jars | --no-progress-bar | \\",
    "line": 8
  }, {
    "author": {
      "login": "davies"
    },
    "body": "The diff will be minimized if it's pleased in the end,  easy to review and blame (in future).\n",
    "commit": "06814035d454a9b7e444b0dc657a572a6ae2f899",
    "createdAt": "2015-01-07T23:38:32Z",
    "diffHunk": "@@ -32,10 +32,11 @@ function gatherSparkSubmitOpts() {\n   APPLICATION_OPTS=()\n   while (($#)); do\n     case \"$1\" in\n-      --master | --deploy-mode | --class | --name | --jars | --py-files | --files | \\\n-      --conf | --properties-file | --driver-memory | --driver-java-options | \\\n-      --driver-library-path | --driver-class-path | --executor-memory | --driver-cores | \\\n-      --total-executor-cores | --executor-cores | --queue | --num-executors | --archives)\n+      --master | --deploy-mode | --class | --name | --jars | --no-progress-bar | \\",
    "line": 8
  }],
  "prId": 3709
}]