[{
  "comments": [{
    "author": {
      "login": "gaborgsomogyi"
    },
    "body": "Not sure why this file is here?",
    "commit": "8a0906e11eab36cb92c159915915b77334d34312",
    "createdAt": "2019-03-20T10:24:47Z",
    "diffHunk": "@@ -0,0 +1,53 @@\n+/*"
  }, {
    "author": {
      "login": "ScrapCodes"
    },
    "body": "Sorry, I was testing with it. I will remove it.",
    "commit": "8a0906e11eab36cb92c159915915b77334d34312",
    "createdAt": "2019-03-20T10:27:17Z",
    "diffHunk": "@@ -0,0 +1,53 @@\n+/*"
  }],
  "prId": 19096
}]