[{
  "comments": [{
    "author": {
      "login": "dongjoon-hyun"
    },
    "body": "Sorry, @seancxmao . We need to update once more. ~I'll make a PR to you.~",
    "commit": "26b4710bb47e700d3532da5652fd5ea3f128be20",
    "createdAt": "2018-09-08T03:21:31Z",
    "diffHunk": "@@ -116,6 +116,14 @@ object OrcUtils extends Logging {\n         })\n       } else {\n         val resolver = if (isCaseSensitive) caseSensitiveResolution else caseInsensitiveResolution\n+        // Need to fail if there is ambiguity, i.e. more than one field is matched.\n+        requiredSchema.fieldNames.foreach { requiredFieldName =>\n+          val matchedOrcFields = orcFieldNames.filter(resolver(_, requiredFieldName))"
  }, {
    "author": {
      "login": "seancxmao"
    },
    "body": "That's all right :)",
    "commit": "26b4710bb47e700d3532da5652fd5ea3f128be20",
    "createdAt": "2018-09-08T05:25:23Z",
    "diffHunk": "@@ -116,6 +116,14 @@ object OrcUtils extends Logging {\n         })\n       } else {\n         val resolver = if (isCaseSensitive) caseSensitiveResolution else caseInsensitiveResolution\n+        // Need to fail if there is ambiguity, i.e. more than one field is matched.\n+        requiredSchema.fieldNames.foreach { requiredFieldName =>\n+          val matchedOrcFields = orcFieldNames.filter(resolver(_, requiredFieldName))"
  }],
  "prId": 22262
}]