[{
  "comments": [{
    "author": {
      "login": "srowen"
    },
    "body": "I don't think we need license headers in doc files -- I don't think others have this.\r\nYou could add one to `DESCRIPTION` for good measure but it's really conf.",
    "commit": "63a035621934d99bd4cb475985090f08c46e1dfc",
    "createdAt": "2017-01-26T10:06:03Z",
    "diffHunk": "@@ -10,6 +10,23 @@ vignette: >\n   \\usepackage[utf8]{inputenc}\n ---\n \n+<!--",
    "line": 4
  }, {
    "author": {
      "login": "felixcheung"
    },
    "body": "I have worked with a few Apache projects that do this in doc though.\r\nI understand we don't. I'm fine either way but since the JIRA is opened, there really isn't any file without license except for DESCRIPTION (doesn't support comment, already has a license tag) and NAMESPACE (which is really a build file, and very often tool generated).",
    "commit": "63a035621934d99bd4cb475985090f08c46e1dfc",
    "createdAt": "2017-01-26T19:28:52Z",
    "diffHunk": "@@ -10,6 +10,23 @@ vignette: >\n   \\usepackage[utf8]{inputenc}\n ---\n \n+<!--",
    "line": 4
  }, {
    "author": {
      "login": "srowen"
    },
    "body": "FWIW the ASF policy statement talks about source files only: http://www.apache.org/legal/release-policy.html#license-headers\r\nIs this source for docs? maybe so. I think it's fine as-is then.",
    "commit": "63a035621934d99bd4cb475985090f08c46e1dfc",
    "createdAt": "2017-01-26T19:47:56Z",
    "diffHunk": "@@ -10,6 +10,23 @@ vignette: >\n   \\usepackage[utf8]{inputenc}\n ---\n \n+<!--",
    "line": 4
  }, {
    "author": {
      "login": "felixcheung"
    },
    "body": "right, this file actually contains source code that gets run to generate output that gets included in generated doc (as a html file) in the Apache source release.",
    "commit": "63a035621934d99bd4cb475985090f08c46e1dfc",
    "createdAt": "2017-01-26T20:17:50Z",
    "diffHunk": "@@ -10,6 +10,23 @@ vignette: >\n   \\usepackage[utf8]{inputenc}\n ---\n \n+<!--",
    "line": 4
  }],
  "prId": 16709
}]