[{
  "comments": [{
    "author": {
      "login": "sethah"
    },
    "body": "avoid wildcard\n",
    "commit": "1d41615863e7d4a0cc225a9a32cc1b175af22a49",
    "createdAt": "2016-10-05T23:35:15Z",
    "diffHunk": "@@ -28,12 +29,12 @@ import org.apache.spark.ml.util._\n import org.apache.spark.mllib.util.MLUtils\n import org.apache.spark.sql.{Dataset, Row}\n import org.apache.spark.sql.functions.{col, lit}\n-import org.apache.spark.sql.types.DoubleType\n+import org.apache.spark.sql.types._"
  }],
  "prId": 15314
}]