[{
  "comments": [{
    "author": {
      "login": "srowen"
    },
    "body": "Typo here. Please make sure build/test/style passes locally before pushing again, or else this takes a lot of work to review.",
    "commit": "e891f53dfd609ef9cb46f70147c59f1113c7c0cb",
    "createdAt": "2017-12-29T13:43:53Z",
    "diffHunk": "@@ -41,8 +41,8 @@ object VectorIndexerExample {\n     val indexerModel = indexer.fit(data)\n \n     val categoricalFeatures: Set[Int] = indexerModel.categoryMaps.keys.toSet\n-    println(s\"Chose ${categoricalFeatures.size} categorical features: \" +\n-      categoricalFeatures.mkString(\", \"))\n+    println(s\"Chose ${categoricalFeatures.size} \" +\n+      s\"categorical features: {$categoricalFeatures.mkString(\", \")}\")"
  }, {
    "author": {
      "login": "chetkhatri"
    },
    "body": "I did fixed this. Can you please give me steps as a check list before commit for test.",
    "commit": "e891f53dfd609ef9cb46f70147c59f1113c7c0cb",
    "createdAt": "2017-12-29T17:26:14Z",
    "diffHunk": "@@ -41,8 +41,8 @@ object VectorIndexerExample {\n     val indexerModel = indexer.fit(data)\n \n     val categoricalFeatures: Set[Int] = indexerModel.categoryMaps.keys.toSet\n-    println(s\"Chose ${categoricalFeatures.size} categorical features: \" +\n-      categoricalFeatures.mkString(\", \"))\n+    println(s\"Chose ${categoricalFeatures.size} \" +\n+      s\"categorical features: {$categoricalFeatures.mkString(\", \")}\")"
  }, {
    "author": {
      "login": "srowen"
    },
    "body": "`./dev/run-tests`",
    "commit": "e891f53dfd609ef9cb46f70147c59f1113c7c0cb",
    "createdAt": "2017-12-30T16:42:46Z",
    "diffHunk": "@@ -41,8 +41,8 @@ object VectorIndexerExample {\n     val indexerModel = indexer.fit(data)\n \n     val categoricalFeatures: Set[Int] = indexerModel.categoryMaps.keys.toSet\n-    println(s\"Chose ${categoricalFeatures.size} categorical features: \" +\n-      categoricalFeatures.mkString(\", \"))\n+    println(s\"Chose ${categoricalFeatures.size} \" +\n+      s\"categorical features: {$categoricalFeatures.mkString(\", \")}\")"
  }],
  "prId": 20070
}]