[{
  "comments": [{
    "author": {
      "login": "cloud-fan"
    },
    "body": "do we still need to change this method?",
    "commit": "95bac2773ee7adab9f57aa4377ff2e998353f02f",
    "createdAt": "2018-01-19T02:27:23Z",
    "diffHunk": "@@ -95,15 +95,15 @@ protected synchronized void send(Message msg) throws IOException {\n   }\n \n   @Override\n-  public void close() throws IOException {\n+  public synchronized void close() throws IOException {"
  }, {
    "author": {
      "login": "vanzin"
    },
    "body": "We never *needed* to change it, but the extra code wasn't doing anything useful, so I chose the simpler version.",
    "commit": "95bac2773ee7adab9f57aa4377ff2e998353f02f",
    "createdAt": "2018-01-19T18:14:32Z",
    "diffHunk": "@@ -95,15 +95,15 @@ protected synchronized void send(Message msg) throws IOException {\n   }\n \n   @Override\n-  public void close() throws IOException {\n+  public synchronized void close() throws IOException {"
  }],
  "prId": 20297
}, {
  "comments": [{
    "author": {
      "login": "gengliangwang"
    },
    "body": "=> isOpen",
    "commit": "95bac2773ee7adab9f57aa4377ff2e998353f02f",
    "createdAt": "2018-01-19T06:52:32Z",
    "diffHunk": "@@ -95,15 +95,15 @@ protected synchronized void send(Message msg) throws IOException {\n   }\n \n   @Override\n-  public void close() throws IOException {\n+  public synchronized void close() throws IOException {\n     if (!closed) {"
  }],
  "prId": 20297
}]