[{
  "comments": [{
    "author": {
      "login": "mccheah"
    },
    "body": "`Some(peakExecutorMetrics).filter(_.isSet)`",
    "commit": "571285beace1a0c1df92d9f5127828ed8955c93f",
    "createdAt": "2018-07-30T21:53:05Z",
    "diffHunk": "@@ -302,10 +305,10 @@ private class LiveExecutor(val executorId: String, _addTime: Long) extends LiveE\n       Option(removeReason),\n       executorLogs,\n       memoryMetrics,\n-      blacklistedInStages)\n+      blacklistedInStages,\n+      if (peakExecutorMetrics.isSet()) Some(peakExecutorMetrics) else None)"
  }, {
    "author": {
      "login": "edwinalu"
    },
    "body": "Changed.",
    "commit": "571285beace1a0c1df92d9f5127828ed8955c93f",
    "createdAt": "2018-08-05T01:05:23Z",
    "diffHunk": "@@ -302,10 +305,10 @@ private class LiveExecutor(val executorId: String, _addTime: Long) extends LiveE\n       Option(removeReason),\n       executorLogs,\n       memoryMetrics,\n-      blacklistedInStages)\n+      blacklistedInStages,\n+      if (peakExecutorMetrics.isSet()) Some(peakExecutorMetrics) else None)"
  }],
  "prId": 21221
}]