[
  {
    "id" : "7fe5912e-cef7-4c5a-b387-5cacd5e50ccb",
    "prId" : 1523,
    "comments" : [
      {
        "id" : "2a1e6eb5-f4db-450e-9943-91d30f3d3b11",
        "parentId" : null,
        "author" : {
          "login" : "kpbochenek",
          "name" : null,
          "avatarUrl" : "https://avatars2.githubusercontent.com/u/10478402?u=7a7840d3f5ce4047a19639e6b7977d43e3557158&v=4"
        },
        "body" : "logging or scribe which one is preferred? (Question)",
        "createdAt" : "2020-03-31T15:29:26Z",
        "updatedAt" : "2020-04-15T13:50:25Z",
        "lastEditedBy" : {
          "login" : "kpbochenek",
          "name" : null,
          "avatarUrl" : "https://avatars2.githubusercontent.com/u/10478402?u=7a7840d3f5ce4047a19639e6b7977d43e3557158&v=4"
        },
        "tags" : [
          {
            "value" : "outdated"
          }
        ]
      },
      {
        "id" : "e126f9b5-0eaa-47fc-95a3-e269c6b3669c",
        "parentId" : "2a1e6eb5-f4db-450e-9943-91d30f3d3b11",
        "author" : {
          "login" : "tgodzik",
          "name" : null,
          "avatarUrl" : "https://avatars0.githubusercontent.com/u/3807253?u=094831e6a696f583ddfd86d3e5923fd8545c543a&v=4"
        },
        "body" : "I don't think scribe is accessible in mtags.",
        "createdAt" : "2020-04-03T16:58:31Z",
        "updatedAt" : "2020-04-15T13:50:25Z",
        "lastEditedBy" : {
          "login" : "tgodzik",
          "name" : null,
          "avatarUrl" : "https://avatars0.githubusercontent.com/u/3807253?u=094831e6a696f583ddfd86d3e5923fd8545c543a&v=4"
        },
        "tags" : [
          {
            "value" : "outdated"
          }
        ]
      }
    ],
    "commit" : "1142490703f832961ac0df1debd14b4f3b12ce7d",
    "line" : null,
    "diffHunk" : "@@ -125,7 +127,7 @@ final class TokenEditDistance private (\n             }\n           Some(revised.toLSP)\n         case (start, end) =>\n-          scribe.warn(s\"stale range: $start $end\")\n+          logger.warning(s\"stale range: $start $end\")"
  }
]