[{
  "comments": [{
    "author": {
      "login": "wangyum"
    },
    "body": "This is for our v2.3.5.",
    "commit": "7b506e8cf33ad055adcb4daeda9bd8e18d233fbe",
    "createdAt": "2019-08-08T02:15:27Z",
    "diffHunk": "@@ -199,7 +199,7 @@ public static TColumnValue toTColumnValue(TypeDescriptor typeDescriptor, Object\n     case DECIMAL_TYPE:\n       return stringValue((HiveDecimal)value, typeDescriptor);\n     case BINARY_TYPE:\n-      return stringValue((String)value);\n+      return stringValue(new String((byte[])value));"
  }, {
    "author": {
      "login": "HyukjinKwon"
    },
    "body": "Oops",
    "commit": "7b506e8cf33ad055adcb4daeda9bd8e18d233fbe",
    "createdAt": "2019-08-08T02:19:08Z",
    "diffHunk": "@@ -199,7 +199,7 @@ public static TColumnValue toTColumnValue(TypeDescriptor typeDescriptor, Object\n     case DECIMAL_TYPE:\n       return stringValue((HiveDecimal)value, typeDescriptor);\n     case BINARY_TYPE:\n-      return stringValue((String)value);\n+      return stringValue(new String((byte[])value));"
  }],
  "prId": 25379
}]