[{
  "comments": [{
    "author": {
      "login": "dongjoon-hyun"
    },
    "body": "- nit. `s\"` -> `\"`?\r\n- `CompactibleFileStreamLog hence not supported` seems to need some revision.",
    "commit": "f8adab32b0eec1ae96f124a563f4393bf3db6659",
    "createdAt": "2019-06-09T03:50:34Z",
    "diffHunk": "@@ -163,6 +163,16 @@ abstract class CompactibleFileStreamLog[T <: AnyRef : ClassTag](\n     batchAdded\n   }\n \n+  /**\n+   * CompactibleFileStreamLog maintains logs by itself, and manual purging might break internal\n+   * state, specifically which latest compaction batch is purged.\n+   *\n+   * To simplify the situation, this method just throws UnsupportedOperationException regardless\n+   * of given parameter, and let CompactibleFileStreamLog handles purging by itself.\n+   */\n+  override def purge(thresholdBatchId: Long): Unit = throw new UnsupportedOperationException(\n+    s\"'purge' might break internal state of CompactibleFileStreamLog hence not supported\")"
  }],
  "prId": 23850
}]