[{
  "comments": [{
    "author": {
      "login": "sethah"
    },
    "body": "this is never used directly, so I can't think of why this shouldn't be a trait. It would break compatibility at this point, but since it's experimental it may be permissible?",
    "commit": "71ccccab915efb0013fb70dc1e0e5a762bf4ad31",
    "createdAt": "2017-11-06T22:01:10Z",
    "diffHunk": "@@ -30,11 +30,12 @@ import org.apache.spark.sql.{DataFrame, Row}\n  * @param k  Number of clusters.\n  */\n @Experimental\n-class ClusteringSummary private[clustering] (\n-    @transient val predictions: DataFrame,\n-    val predictionCol: String,\n-    val featuresCol: String,\n-    val k: Int) extends Serializable {\n+// TODO: make this a trait?\n+class ClusteringSummary private[ml] (",
    "line": 19
  }],
  "prId": 19680
}]