[{
  "comments": [{
    "author": {
      "login": "squito"
    },
    "body": "the tests are failing b/c this is not binary compatible, but I think this is OK.  In particular, from http://spark.apache.org/docs/latest/monitoring.html\nwe say:\n\n> New fields may be added to existing endpoints\n\nSo we should add a mima exclusion [here](https://github.com/apache/spark/blob/master/project/MimaExcludes.scala#L37).  The logs of the PR builder tell you exactly what to add:\n`ProblemFilters.exclude[MissingMethodProblem](\"org.apache.spark.status.api.v1.ExecutorSummary.this\")`\n",
    "commit": "d94a7164174eb826b35a7b7caa8a3b9de240f5d2",
    "createdAt": "2015-07-22T20:33:47Z",
    "diffHunk": "@@ -60,7 +60,8 @@ class ExecutorSummary private[spark](\n     val totalShuffleRead: Long,\n     val totalShuffleWrite: Long,\n     val maxMemory: Long,\n-    val executorLogs: Map[String, String])\n+    val executorLogs: Map[String, String],\n+    val isRemoved: Boolean)"
  }, {
    "author": {
      "login": "JoshRosen"
    },
    "body": "Mind adding a `//` comment next to `isRemoved` to say something like \"Added in 1.5.0\" or \"since 1.5.0\"?\n",
    "commit": "d94a7164174eb826b35a7b7caa8a3b9de240f5d2",
    "createdAt": "2015-07-22T20:42:43Z",
    "diffHunk": "@@ -60,7 +60,8 @@ class ExecutorSummary private[spark](\n     val totalShuffleRead: Long,\n     val totalShuffleWrite: Long,\n     val maxMemory: Long,\n-    val executorLogs: Map[String, String])\n+    val executorLogs: Map[String, String],\n+    val isRemoved: Boolean)"
  }, {
    "author": {
      "login": "suyanNone"
    },
    "body": "Ok, I will refine that, and it's nice to tell me about MimaExcludes\n",
    "commit": "d94a7164174eb826b35a7b7caa8a3b9de240f5d2",
    "createdAt": "2015-07-28T06:18:45Z",
    "diffHunk": "@@ -60,7 +60,8 @@ class ExecutorSummary private[spark](\n     val totalShuffleRead: Long,\n     val totalShuffleWrite: Long,\n     val maxMemory: Long,\n-    val executorLogs: Map[String, String])\n+    val executorLogs: Map[String, String],\n+    val isRemoved: Boolean)"
  }],
  "prId": 6644
}]