[{
  "comments": [{
    "author": {
      "login": "cloud-fan"
    },
    "body": "nit: not `Expanded`",
    "commit": "b5a48daab41f8462843a062475413400482d1213",
    "createdAt": "2017-01-23T11:08:11Z",
    "diffHunk": "@@ -528,8 +528,10 @@ case class DescribeTableCommand(\n   private def describeViewInfo(metadata: CatalogTable, buffer: ArrayBuffer[Row]): Unit = {\n     append(buffer, \"\", \"\", \"\")\n     append(buffer, \"# View Information\", \"\", \"\")\n-    append(buffer, \"View Original Text:\", metadata.viewOriginalText.getOrElse(\"\"), \"\")\n     append(buffer, \"View Expanded Text:\", metadata.viewText.getOrElse(\"\"), \"\")"
  }],
  "prId": 16679
}]