[{
  "comments": [{
    "author": {
      "login": "sandeep-katta"
    },
    "body": "implement KryoSerializable also",
    "commit": "faec81759a3305b87493e24713039248497bd97b",
    "createdAt": "2019-04-08T12:17:33Z",
    "diffHunk": "@@ -52,7 +58,7 @@\n  * Instances of `UnsafeArrayData` act as pointers to row data stored in this format.\n  */\n \n-public final class UnsafeArrayData extends ArrayData {\n+public final class UnsafeArrayData extends ArrayData implements Externalizable {",
    "line": 25
  }],
  "prId": 24317
}]